rpi_lcd_i2c_animations/__init__.py
rpi_lcd_i2c_animations/animate_67.py
rpi_lcd_i2c_animations-0.1.0.dist-info/licenses/LICENSE
rpi_lcd_i2c_animations-0.1.0.dist-info/METADATA
rpi_lcd_i2c_animations-0.1.0.dist-info/WHEEL
rpi_lcd_i2c_animations-0.1.0.dist-info/top_level.txt
rpi_lcd_i2c_animations-0.1.0.dist-info/RECORD
