Metadata-Version: 2.4
Name: rpi-lcd-i2c-animations
Version: 0.1.0
Summary: LCD animation add-ons for rpi_lcd_i2c
Home-page: https://github.com/Sam67-coder/rpi_lcd_i2c_animations
Author: Sammy
License: MIT
Project-URL: Homepage, https://github.com/Sam67-coder/rpi_lcd_i2c_animations
Project-URL: Repository, https://github.com/Sam67-coder/rpi_lcd_i2c_animations
Requires-Python: >=3.9
License-File: LICENSE
Requires-Dist: rpi-lcd-i2c
Dynamic: home-page
Dynamic: license-file
Dynamic: requires-python
